snap_http/__init__.py
snap_http/api.py
snap_http/http.py
snap_http/types.py
snap_http-1.11.0.dist-info/LICENSE
snap_http-1.11.0.dist-info/METADATA
snap_http-1.11.0.dist-info/WHEEL
snap_http-1.11.0.dist-info/RECORD
